Workbook

Sheet 00_Anleitung
A1: Defeated by Titan — Produktions-Backlog
A2: Vollstaendige To-do-Liste aller Spielfunktionen und Assets. Jede Zeile ist ein Ticket. Zielplattform: PC, Tastatur und Maus, kooperativer Mehrspieler.
A5: BLATT | B5: INHALT
A6: 01_Spielfunktionen | B6: Alle Features mit ID, Beschreibung, Akzeptanzkriterium, Prioritaet, Aufwand und Abhaengigkeit.
A7: 02_3D-Assets | B7: Alle Modelle mit Beschreibung, Polygonbudget je Detailstufe, Variantenzahl und Textur-Slot.
A8: 03_Animationen | B8: Alle Animationsclips je Rig, mit Beschreibung, Dauer und Loop-Verhalten.
A9: 04_Texturen | B9: Alle Texturen und Atlanten mit Aufloesung, Typ und Verwendungszweck.
A10: 05_VFX | B10: Alle visuellen Effekte mit Technik und Ausloeser.
A11: 06_Audio | B11: Alle Sound- und Musikassets mit Beschreibung, Laenge und Loop-Verhalten.
A12: 07_UI-Screens | B12: Alle Bildschirme mit den jeweils enthaltenen Elementen.
A13: 08_Maps | B13: Alle Level mit Beschreibung, unterstuetzten Modi, Groesse und Ankerdichte.
A14: 09_Tech-Backlog | B14: Technische Aufgaben: Pipeline, Netzwerk, Performance, Daten, Betrieb, QA.
A15: 10_Namensschema | B15: Uebersetzung der Referenzbegriffe in die eigene Spielwelt.
A16: 11_Zusammenfassung | B16: Automatische Auszaehlung nach Prioritaet und Aufwand.
... A29: WICHTIGSTE REGEL | B29: Kein Meta-System vor bestandenem Vector-Gear-Gate. Erst wenn die Bewegung im Blindtest ueberzeugt, wird gebaut.

Sheet 01_Spielfunktionen
A1: 01_Spielfunktionen
A2: Alle Spielfunktionen. Prio-Spalte ist eingefaerbt. Filter ueber die Kopfzeile.
A4: ID | B4: System | C4: Feature | D4: Beschreibung | E4: Akzeptanzkriterium | F4: Prio | G4: Aufwand (PT) | H4: Disziplin | I4: Abhaengig von | J4: Status
A5: F-001 | B5: Vector Gear | C5: Doppelhaken-Grundsystem | D5: Zwei unabhaengig steuerbare Enterhaken (links/rechts), einzeln abfeuerbar und loesbar. Jeder Haken hat eigenen Zustand: idle, fliegend, verankert, einziehend. | E5: Beide Haken lassen sich unabhaengig setzen und loesen; Zustaende sind im HUD sichtbar. | F5: Must | G5: 12 | H5: Engineering | J5: Offen
A6: F-002 | B6: Vector Gear | C6: Freies Zielen per Raycast (Ebene 1) | D6: Basisebene des Zielsystems. Raycast aus Kameraposition in Blickrichtung, Reichweite = Range-Stat (Basis 400 studs). Trefferpunkt wird gegen eine gueltige Ankerflaeche geprueft. Der Spieler kann jede getaggte Flaeche frei anvisieren, unabhaengig von gesetzten Ankerpunkten. Diese Ebene bleibt IMMER aktiv und ist niemals durch das Snap-System ersetzbar. | E6: Jede getaggte Flaeche ist per freiem Zielen erreichbar, auch wenn dort kein Ankerpunkt liegt. | F6: Must | G6: 5 | H6: Engineering | I6: F-001 | J6: Offen
A7: F-003 | B7: Vector Gear | C7: Getaggte Ankerflaechen (Ebene 1) | D7: Nur Oberflaechen mit CollectionService-Tag 'AnchorSurface' sind hakbar. Gilt fuer ganze Flaechen, nicht fuer Punkte. Verhindert Physik-Exploits, macht Leveldesign steuerbar und definiert ueber die Flaechendichte die Traversal-Schwierigkeit einer Map. | E7: Kein Haken auf ungetaggten Parts moeglich; Tagging-Werkzeug im Studio vorhanden; Heatmap zeigt Flaechenabdeckung. | F7: Must | G7: 4 | H7: Engineering / LD | I7: F-002 | J7: Offen
A8: F-004 | B8: Vector Gear | C8: Pendelphysik bei Zwei-Haken-Zustand | D8: Zwei gesetzte Haken erzeugen echte Zentripetalbewegung ueber RopeConstraint statt linearem Ziehen. Basis fuer Momentum-Chaining. | E8: Spieler beschreibt sichtbar eine Bogenbahn; Geschwindigkeit steigt beim Ausschwingen. | F8: Must | G8: 15 | H8: Engineering | I8: F-001 | J8: Offen
A9: F-005 | B9: Vector Gear | C9: Reel-In / Seilverkuerzung | D9: Kontrollierte Reduktion der Seillaenge zum Hoehengewinn. Manuell steuerbar, verbraucht Gas. | E9: Spieler kann aus dem Tiefpunkt Hoehe gewinnen; Gasverbrauch ist spuerbar. | F9: Must | G9: 5 | H9: Engineering | I9: F-004 | J9: Offen
A10: F-006 | B10: Vector Gear | C10: Swerve-Steuerung | D10: Richtungseingabe waehrend des Einzugs moduliert die Flugbahn seitlich, nach oben und unten. Kein binaeres Ziel-Anfliegen. | E10: Vier Swerve-Richtungen aendern die Bahn messbar ohne Haken zu loesen. | F10: Must | G10: 8 | H10: Engineering | I10: F-004 | J10: Offen
A11: F-007 | B11: Vector Gear | C11: Gas-Boost | D11: Impuls in Blickrichtung bei gehaltener Taste, verbraucht Gas kontinuierlich. Deutliches VFX/SFX-Feedback. | E11: Boost erzeugt spuerbare Beschleunigung; Gasleiste sinkt sichtbar. | F11: Must | G11: 4 | H11: Engineering | I11: F-001 | J11: Offen
A12: F-008 | B12: Vector Gear | C12: Boost-Dash | D12: Doppeltipp erzeugt einen kurzen, harten Impuls mit eigenem Cooldown. Anzahl der Dashes ist ein Stat. | E12: Dash ist von Boost unterscheidbar; Anzahl korrekt limitiert und regeneriert. | F12: Must | G12: 4 | H12: Engineering | I12: F-007 | J12: Offen
A13: F-009 | B13: Vector Gear | C13: Flips (seitlich) | D13: Doppeltipp A/D erzeugt seitlichen Ausweichsprung in der Luft mit kurzen I-Frames. | E13: Flip vermeidet einen Titanengriff, wenn im Fenster ausgeloest. | F13: Must | G13: 4 | H13: Engineering | I13: F-001 | J13: Offen
A14: F-010 | B14: Vector Gear | C14: Slide-Dodge am Boden | D14: Gleit-Ausweichmanoever am Boden mit I-Frames und Momentum-Erhalt. | E14: Slide vermeidet Stomp-Angriff; geht fliessend in Sprint ueber. | F14: Must | G14: 3 | H14: Engineering | J14: Offen
A15: F-011 | B15: Vector Gear | C15: Hook-Break (Notbremse) | D15: Beide Haken nach hinten abfeuern, harte Verzoegerung. Rettungsmanoever vor Kollision. | E15: Geschwindigkeit sinkt innerhalb von 0,6 s um mindestens 70 Prozent. | F15: Should | G15: 3 | H15: Engineering | I15: F-001 | J15: Offen
A16: F-012 | B16: Vector Gear | C16: Velocity-Clamp gegen Fling | D16: Harte Obergrenze auf AssemblyLinearVelocity bei jedem Heartbeat. Verhindert den klassischen Roblox-Physikfehler. | E16: Kein Testfall erzeugt Geschwindigkeit ueber dem Cap; kein Spieler wird aus der Map geschleudert. | F16: Must | G16: 3 | H16: Engineering | I16: F-004 | J16: Offen
A17: F-013 | B17: Vector Gear | C17: Kollisionsdaempfung | D17: Aufprall auf Geometrie verlangsamt und staggert statt zu toeten. Recovery-Fenster mit Wandkontakt-Animation. | E17: Frontalaufprall bei Hoechstgeschwindigkeit fuehrt nicht zum Tod; Erholung dauert unter 1 s. | F17: Must | G17: 6 | H17: Engineering | I17: F-004 | J17: Offen
A18: F-014 | B18: Vector Gear | C18: Momentum-Chaining | D18: Beim Wechsel von Haken zu Haken bleibt Geschwindigkeit erhalten. Kern-Skillausdruck des gesamten Spiels. | E18: Ein geuebter Spieler kann Geschwindigkeit ueber 5 Hakenwechsel steigern statt zu verlieren. | F18: Must | G18: 10 | H18: Engineering | I18: F-004 | J18: Offen
A19: F-015 | B19: Vector Gear | C19: Wall-Run und Wall-Kick | D19: Kurzer Lauf an vertikalen Flaechen plus Absprung. Alternative Traversal-Ebene fuer enge Raeume. | E19: Wall-Run ueber mindestens 3 s moeglich; Kick erzeugt nutzbaren Impuls. | F19: Could | G19: 7 | H19: Engineering | I19: F-013 | J19: Offen
A20: F-016 | B20: Vector Gear | C20: Ziel-Assist-Regler | D20: Stufenlos einstellbarer Snap-Fangwinkel von 0 bis 100 Prozent. Steuert, wie weit das Fadenkreuz von einem Ankerpunkt abweichen darf, damit der Snap greift. Bei 0 verhaelt sich das System wie reines freies Zielen. Siehe F-024 fuer die drei Zielmodi. | E20: Regler wirkt messbar auf den Fangwinkel; der verwendete Wert wird bei jedem Bestenlisten-Eintrag mitgespeichert. | F20: Should | G20: 4 | H20: Engineering / UX | I20: F-024 | J20: Offen
A21: F-017 | B21: Vector Gear | C21: Geschwindigkeits-Feedback | D21: Speedlines, Kamera-FOV-Kurve, Windrauschen und Vignette skalieren mit Velocity. Verkauft Tempo ohne echte Physikaenderung. | E21: FOV und Audio reagieren stufenlos; abschaltbar fuer Motion Sickness. | F21: Must | G21: 5 | H21: Engineering / VFX | I21: F-004 | J21: Offen
A22: F-018 | B22: Vector Gear | C22: Gas-Ressource | D22: Blaue Leiste, Verbrauch durch Reel-In, Boost und Dash. Bei 0 kein Fliegen mehr, nur noch Bodenbewegung. | E22: Gasverbrauch pro Aktion ist in Config definiert und im HUD ablesbar. | F22: Must | G22: 3 | H22: Engineering | I22: F-007 | J22: Offen
A23: F-019 | B23: Vector Gear | C23: Nachschub-Stationen | D23: Statische Punkte auf der Map fuellen Gas und Klingen. Begrenzte Nachladungen pro Mission. | E23: Nachladen dauert 1,5 s; Zaehler sichtbar; leere Station wird visuell markiert. | F23: Must | G23: 5 | H23: Engineering / LD | I23: F-018 | J23: Offen
A24: F-020 | B24: Vector Gear | C24: Tragbarer Notvorrat | D24: Verbrauchsgegenstand fuer eine Feldbetankung ohne Station, mit langer Animation als Risikofaktor. | E24: Item funktioniert nur am Boden oder haengend; Animation ist unterbrechbar mit Verlust. | F24: Could | G24: 3 | H24: Engineering | I24: F-019 | J24: Offen
A25: F-021 | B25: Ankersystem | C25: Diskrete Ankerpunkte (Ebene 2) | D25: Zweite Ebene ueber den Ankerflaechen: konkrete, einzeln adressierbare Punkte im Level (Dachkanten, Schornsteine, Vorspruenge, Astgabeln, Laternen, Kranausleger, Titanenkoerper). Jeder Punkt traegt Metadaten: Typ, Hoehe, Ausrichtung der Normalen, Guete-Basiswert, ob dynamisch (an bewegtem Objekt) oder statisch. | E25: Jede Map besitzt eine vollstaendige Ankerpunktliste; Punkte sind einzeln inspizierbar und im Editor sichtbar. | F25: Must | G25: 8 | H25: Engineering / LD | I25: F-003 | J25: Offen
A26: F-022 | B26: Ankersystem | C26: Prozedurale Ankerpunkt-Erzeugung | D26: Werkzeug erzeugt Ankerpunkte automatisch aus der Geometrie getaggter Flaechen (Kantenerkennung, Vorsprungerkennung, Mindestabstand zwischen Punkten). Level Designer korrigiert danach nur noch von Hand, statt tausende Punkte einzeln zu setzen. | E26: Eine komplette Stadtmap wird in unter 5 Minuten mit Punkten befuellt; manuelle Nacharbeit unter 10 Prozent der Punkte. | F26: Must | G26: 10 | H26: Tech Art / LD | I26: F-021 | J26: Offen
... A36: F-032a | B36: Ankersystem | C36: Trainingsanzeige fuer Ankerpunkte | D36: Im Trainingsgelaende einblendbarer Modus, der ALLE Punkte einer Zone sichtbar macht, samt Bewertungswerten und der Bahn, die das System bei Q oder E waehlen wuerde. Lehrwerkzeug fuer das Verstaendnis der eigenen Traversal. | E36: Ein Spieler kann nachvollziehen, warum das System einen bestimmten Punkt gewaehlt hat. | F36: Should | G36: 5 | H36: Design / UI | I36: F-025 | J36: Offen
A37: F-030 | B37: Kampf | C37: Nape-Trefferzone (Cortex) | D37: Separate Kollisionsgeometrie am Nacken jedes Titanen als einziger Kill-Punkt. Visuell markiert durch dampfende, leicht leuchtende Textur. | E37: Cortex ist aus 100 studs Entfernung erkennbar; Treffer registriert zuverlaessig. | F37: Must | G37: 6 | H37: Engineering / Art | J37: Offen
A38: F-031 | B38: Kampf | C38: Geschwindigkeitsabhaengige Schadensformel | D38: Schaden skaliert mit relativer Anfluggeschwindigkeit und Schnittwinkel. Bewegung ist Schaden. | E38: Ein Schnitt bei doppelter Geschwindigkeit erzeugt mindestens 60 Prozent mehr Schaden. | F38: Must | G38: 5 | H38: Engineering / Design | I38: F-030 | J38: Offen
A39: F-032 | B39: Kampf | C39: Sekundaere Trefferzonen | D39: Arme, Beine, Augen mit eigenen Hitboxen. Kein Kill, sondern Stagger, Bewegungs-Debuff oder Blendung. | E39: Bein-Treffer laesst Titan stuerzen; Augen-Treffer erzeugt 3 s Orientierungslosigkeit. | F39: Must | G39: 7 | H39: Engineering | I39: F-030 | J39: Offen
A40: F-033 | B40: Kampf | C40: Klingenhaltbarkeit | D40: Rote Leiste, Verbrauch pro Schlag, abhaengig von getroffener Zone. Bruch mit lautem Feedback und Animation. | E40: Klingenbruch entfernt Schadenspotenzial vollstaendig bis zum Nachladen. | F40: Must | G40: 4 | H40: Engineering | I40: F-030 | J40: Offen
A41: F-034 | B41: Kampf | C41: Hit-Stop und Impact-Frames | D41: Kurzer Zeitstopp bei Nape-Kill mit Kamera-Kick und Sound-Layer. Wichtigstes Belohnungssignal im Spiel. | E41: Kill fuehlt sich in Blindtests messbar befriedigender an als ohne Hit-Stop. | F41: Must | G41: 4 | H41: Engineering / VFX | I41: F-030 | J41: Offen
A42: F-035 | B42: Kampf | C42: Lance Charges (Fernwaffe) | D42: Explosive Wurflanzen mit Haftung, manueller Detonation in Naehe und Auto-Detonation nach Zeit oder Distanz. Eigene Statlinie. | E42: Manuelle und automatische Detonation funktionieren; Blast-Radius als Stat wirksam. | F42: Should | G42: 10 | H42: Engineering | I42: F-030 | J42: Offen
A43: F-036 | B43: Kampf | C43: Lance-Munition und Nachschub | D43: Begrenzte Anzahl Lanzen pro Mission, Nachschub nur an Stationen. Ammunition ist ein Stat. | E43: Munitionszaehler im HUD; Nachladen an Station funktioniert. | F43: Should | G43: 3 | H43: Engineering | I43: F-035 | J43: Offen
A44: F-037 | B44: Kampf | C44: Kein Friendly Fire | D44: Explosionen und Klingen verursachen keinen Schaden an Mitspielern, wohl aber Knockback als taktisches Element. | E44: Kein Spieler kann einen anderen toeten; Knockback ist einstellbar. | F44: Must | G44: 2 | H44: Engineering | I44: F-035 | J44: Offen
A45: F-038 | B45: Kampf | C45: Verletzungssystem | D45: Treffer durch Titanen koennen gestufte Verletzungen zufuegen (leicht/schwer/kritisch), die Stats senken. Sichtbar im HUD. | E45: Verletzungen sind unterscheidbar, wirken auf Stats und sind im Feld temporaer behandelbar. | F45: Should | G45: 8 | H45: Engineering / Design | I45: F-032 | J45: Offen
A46: F-039 | B46: Kampf | C46: Feldbehandlung und Medic | D46: Verletzungen im Hub heilbar; im Feld nur temporaer stabilisierbar durch Verbandsitem oder Support-Skill. | E46: Medic-NPC heilt alle Stufen; Feldverband hebt nur eine Stufe fuer begrenzte Zeit. | F46: Should | G46: 4 | H46: Engineering | I46: F-038 | J46: Offen
A47: F-040 | B47: Kampf | C47: Gerichteter Griff-Escape | D47: Bei Titanengriff zeigt das UI eine Richtung; Spieler muss den Haken in die Gegenrichtung schiessen. Ersetzt Button-Mashing durch eine Koennenspruefung. | E47: Escape gelingt bei korrekter Richtung, scheitert bei falscher; kein Vorteil durch schnelleres Tastenhaemmern messbar. | F47: Must | G47: 6 | H47: Engineering / UX | I47: F-030 | J47: Offen
A48: F-041 | B48: Kampf | C48: Combo-System | D48: Aufeinanderfolgende Treffer ohne Bodenkontakt erhoehen einen Multiplikator, der bei Treffer oder Landung zurueckgesetzt wird. | E48: Multiplikator sichtbar, wirkt auf Gold und Schaden, bricht korrekt ab. | F48: Should | G48: 5 | H48: Engineering / Design | I48: F-031 | J48: Offen
A49: F-042 | B49: Kampf | C49: Finisher-Kamera | D49: Kurze Zeitlupe beim letzten Titanen einer Welle oder bei einem Multi-Kill. Abschaltbar. | E49: Ausloesebedingungen greifen; Kamera bricht bei Gefahr sofort ab. | F49: Could | G49: 5 | H49: Engineering / VFX | I49: F-034 | J49: Offen
A50: F-043 | B50: Kampf | C50: Schadenszahlen und Trefferfeedback | D50: Schwebende Zahlen, Trefferblitz, unterschiedliche Sounds fuer Normal/Crit/Nape. Vollstaendig abschaltbar. | E50: Drei Trefferarten sind akustisch und visuell unterscheidbar. | F50: Should | G50: 3 | H50: Engineering / UI | I50: F-031 | J50: Offen
A51: F-044 | B51: Kampf | C51: Nahkampf am Boden | D51: Grundlegender Bodenangriff fuer Situationen ohne Gas, deutlich schwaecher als Luftangriff. | E51: Bodenangriff existiert, ist aber niemals die effizientere Wahl. | F51: Could | G51: 3 | H51: Engineering | J51: Offen
A52: F-050 | B52: Titan-KI | C52: Zustandsmaschine | D52: Kern-FSM: Idle, Alerted, Pursue, Attack, Stagger, Recover, Death. Modular erweiterbar pro Typ. | E52: Alle Zustaende sind im Debug-Overlay sichtbar und wechseln korrekt. | F52: Must | G52: 12 | H52: Engineering | J52: Offen
A53: F-051 | B53: Titan-KI | C53: Wahrnehmungsmodell | D53: Sichtkegel mit Reichweite und Winkel plus Hoerradius. Gas-Boost erzeugt Laerm und zieht Aufmerksamkeit. | E53: Ein leise agierender Spieler wird spaeter entdeckt als ein boostender. | F53: Should | G53: 6 | H53: Engineering | I53: F-050 | J53: Offen
A54: F-052 | B54: Titan-KI | C54: Pathfinding mit Groessenlogik | D54: Navigation um Gebaeude; grosse Titanen laufen durch kleine Hindernisse hindurch statt sie zu umgehen. | E54: 15m-Titan zerstoert kleine Props, 3m-Titan umgeht sie. | F54: Must | G54: 8 | H54: Engineering | I54: F-050 | J54: Offen
A55: F-053 | B55: Titan-KI | C55: Telegraphierte Angriffe | D55: Jede Attacke besitzt eine lesbare Windup-Phase von mindestens 0,4 s mit eindeutiger Silhouette. | E55: Testspieler koennen nach 10 Minuten alle Angriffe vorhersehen. | F55: Must | G55: 6 | H55: Engineering / Animation | I55: F-050 | J55: Offen
A56: F-054 | B56: Titan-KI | C56: KI-Level-of-Detail | D56: Nahe Titanen ticken mit 20 Hz, entfernte mit 5 Hz, sehr entfernte nur als Positionsinterpolation. | E56: 60 aktive Titanen erzeugen unter 8 ms Serverlast pro Frame. | F56: Must | G56: 7 | H56: Engineering | I56: F-050 | J56: Offen
A57: F-055 | B57: Titan-KI | C57: Gruppendynamik | D57: Titanen umkreisen den Spieler statt sich zu stapeln; sie beanspruchen Positionsslots um das Ziel. | E57: Bei 6 Titanen auf einen Spieler stehen keine zwei in derselben Position. | F57: Should | G57: 6 | H57: Engineering | I57: F-052 | J57: Offen
A58: F-056 | B58: Titan-KI | C58: Gegnertyp: Husk (Standard) | D58: Basistyp. Langsam, gerade Verfolgung, Standardangriffe. 70 Prozent aller Spawns auf niedrigen Schwierigkeiten. | E58: Spawnt korrekt, greift korrekt an, stirbt bei Cortex-Treffer. | F58: Must | G58: 5 | H58: Design / Engineering | I58: F-050 | J58: Offen
A59: F-057 | B59: Titan-KI | C59: Gegnertyp: Errant (Abnormal) | D59: Unberechenbar, deutlich schneller, ignoriert Naherfolgung zugunsten von Distanzsprints. Zusatzangriffe Bellyflop und Kick. | E59: Verhalten ist sichtbar anders als Husk; Zusatzangriffe werden ausgeloest. | F59: Must | G59: 6 | H59: Design / Engineering | I59: F-056 | J59: Offen
A60: F-058 | B60: Titan-KI | C60: Gegnertyp: Scuttler (Crawler) | D60: Bewegt sich vierfuessig, sehr hohe Geschwindigkeit, reduzierte HP, Dive-Attacke im Sprung. Eigenes Rig. | E60: Scuttler ist die schnellste Bodeneinheit; Dive trifft vorhersagbar. | F60: Must | G60: 8 | H60: Design / Engineering | I60: F-050 | J60: Offen
A61: F-059 | B61: Titan-KI | C61: Gegnertyp: Weaver (Ducker) | D61: Reagiert auf Annaeherung an den Cortex mit Rueckwaertsrolle und I-Frames nach dem Startup. Bestraft mechanisches Spam. | E61: Rolle hat lesbares Startup, danach garantierte Unverwundbarkeit fuer definierte Dauer. | F61: Must | G61: 7 | H61: Design / Engineering | I61: F-050 | J61: Offen
A62: F-060 | B62: Titan-KI | C62: Gegnertyp: Warden | D62: Schuetzt den eigenen Cortex aktiv mit der Hand. Muss von vorne gestaggert oder an den Armen verwundet werden, bevor der Nacken frei liegt. | E62: Frontalangriff auf Arme oeffnet den Cortex fuer ein Zeitfenster. | F62: Should | G62: 8 | H62: Design / Engineering | I62: F-032 | J62: Offen
A63: F-061 | B63: Titan-KI | C63: Gegnertyp: Lurker | D63: Ambush-Einheit. Kauert bewegungslos, greift erst bei Naehe an, kann Spieler aus der Luft greifen. Erzwingt Hoehenwechsel. | E63: Lurker ist im Ruhezustand schwer von Umgebungsgeometrie zu unterscheiden. | F63: Should | G63: 8 | H63: Design / Engineering | I63: F-051 | J63: Offen
A64: F-062 | B64: Titan-KI | C64: Gegnertyp: Bellower | D64: Reagiert extrem auf Gas-Geraeusche und ruft andere Titanen herbei. Fuegt eine Stealth-Ebene hinzu. | E64: Ruf zieht alle Titanen im Radius an; leises Spiel vermeidet den Ruf. | F64: Should | G64: 6 | H64: Design / Engineering | I64: F-051 | J64: Offen
... A68: F-066 | B68: Titan-KI | C68: Object Pooling | D68: Titanen werden wiederverwendet statt neu erzeugt. Gilt auch fuer Projektile und VFX. | E68: Kein messbarer Frame-Spike beim Spawn einer Welle. | F68: Must | G68: 5 | H68: Engineering | I68: F-065 | J68: Offen
A69: F-070 | B69: Missionen | C69: Missions-Zustandsmaschine | D69: Generischer Ablauf: Briefing, Deployment, aktive Phase, Zielabschluss, Extraktion, Ergebnis. | E69: Alle Modi nutzen dieselbe Basismaschine; neue Modi sind reine Config. | F69: Must | G69: 10 | H69: Engineering | J69: Offen
A70: F-071 | B70: Missionen | C70: Modus: Skirmish | D70: Offene Feldschlacht. Toete eine Zielanzahl Titanen innerhalb eines Zeitlimits, ohne dass zu viele NPC-Zivilisten sterben. | E70: Ziel- und Fehlbedingungen greifen; Fortschritt ist im HUD sichtbar. | F70: Must | G70: 6 | H70: Design / Engineering | I70: F-070 | J70: Offen
A71: F-072 | B71: Missionen | C71: Modus: Breach (Verteidigung) | D71: Halte eine Position gegen anrollende Wellen, waehrend eine Struktur Schaden nimmt. Verlust der Struktur = Fehlschlag. | E71: Struktur-HP sichtbar; Wellen eskalieren nach Kurve. | F71: Must | G71: 7 | H71: Design / Engineering | I71: F-070 | J71: Offen
A72: F-073 | B72: Missionen | C72: Modus: Escort | D72: Begleite bewegliche Karren entlang einer Route zum Sicherheitspunkt. Karren sind zerstoerbar. | E72: Karren bewegen sich auf Pfad; Verlust aller Karren beendet die Mission. | F72: Must | G72: 8 | H72: Design / Engineering | I72: F-070 | J72: Offen
A73: F-074 | B73: Missionen | C73: Modus: Stall (Ueberleben) | D73: Ueberlebe eine feste Dauer gegen eskalierende Uebermacht. Kein Kill-Ziel, reine Ausweichpruefung. | E73: Timer laeuft, Spawnrate steigt, Fehlschlag kostet Streak. | F73: Should | G73: 5 | H73: Design / Engineering | I73: F-070 | J73: Offen
A74: F-075 | B74: Missionen | C74: Modus: Protect | D74: Schuetze ein bewegliches, nicht steuerbares NPC-Ziel, das eine Aufgabe erledigt. Ziel hat eigene HP-Leiste. | E74: Ziel-HP sichtbar; Titanen priorisieren das Ziel ueber Spieler. | F74: Should | G74: 6 | H74: Design / Engineering | I74: F-070 | J74: Offen
A75: F-076 | B75: Missionen | C75: Modus: Reclaim (neu) | D75: Erobere und halte drei Kontrollpunkte nacheinander. Punkte erfordern Anwesenheit und Titanfreiheit im Radius. | E75: Eroberung laeuft nur bei geraeumtem Radius; Rueckeroberung durch Titanen moeglich. | F75: Should | G75: 7 | H75: Design / Engineering | I75: F-070 | J75: Offen
A76: F-077 | B76: Missionen | C76: Modus: Traversal Trial (neu) | D76: Reiner Bewegungsmodus. Zeitrennen ueber Checkpoints ohne Kampf, mit Geister-Replay und Bestenliste. | E76: Zeiten werden persistiert; Geist eines besseren Laufs ist abspielbar. | F76: Should | G76: 9 | H76: Design / Engineering | I76: F-014 | J76: Offen
A77: F-078 | B77: Missionen | C77: Randomizer | D77: Zufaellig kombinierte Zielsets aus dem Pool aller Modi. Hoehere Belohnung durch Unvorhersehbarkeit. | E77: Kombinationen sind valide und niemals unmoeglich. | F77: Should | G77: 5 | H77: Design / Engineering | I77: F-070 | J77: Offen
A78: F-079 | B78: Missionen | C78: Sekundaerziele | D78: Zufaellig zugewiesenes optionales Zusatzziel pro Einsatz. Bonusbelohnung bei Abschluss. | E78: Mindestens 8 verschiedene Sekundaerziele; Chance skaliert mit Schwierigkeit. | F78: Should | G78: 6 | H78: Design / Engineering | I78: F-070 | J78: Offen
A79: F-080 | B79: Missionen | C79: Schwierigkeitsgrade | D79: Fuenf Stufen mit skalierenden Titanenzahlen, HP, Typenverteilung und Belohnungen. Gating ueber Ausruestungsrang. | E79: Jede Stufe ist als Config-Datei definiert; Sprung zwischen Stufen ist spuerbar. | F79: Must | G79: 5 | H79: Design | I79: F-070 | J79: Offen
A80: F-081 | B80: Missionen | C80: Modifikatoren (Mutatoren) | D80: Optional zuschaltbare Erschwernisse fuer erhoehte Belohnung: Nebel, kein Nachschub, doppelte Scuttler, Nacht, Regen mit reduzierter Haftung. | E80: Mindestens 10 Modifikatoren, stapelbar, Belohnungsmultiplikator korrekt berechnet. | F80: Should | G80: 8 | H80: Design / Engineering | I80: F-080 | J80: Offen
A81: F-082 | B81: Missionen | C81: Spielerzahl-Skalierung | D81: Titananzahl, Boss-HP und Zielwerte skalieren mit der Spielerzahl im Server. Solo ist vollstaendig spielbar. | E81: Solo-Clear-Zeit weicht um weniger als 25 Prozent von Gruppen-Clear-Zeit ab. | F81: Must | G81: 5 | H81: Design / Engineering | I81: F-080 | J81: Offen
... A103: F-113 | B103: Vessel Form | C103: Gegner-Anpassung | D103: Titanen wechseln gegen eine Vessel Form ihr Verhalten: Gruppenangriffe, Klettern, Cortex-Angriffe. | E103: KI reagiert sichtbar anders auf verwandelte Spieler. | F103: Should | G103: 6 | H103: Engineering | I103: F-107 | J103: Offen
A104: F-120 | B104: Progression | C104: Level und Erfahrungskurve | D104: Level 1 bis 100 mit definierter XP-Kurve. Jedes Level gibt Faehigkeitspunkte. | E104: Kurve ist in Config definiert und ohne Codeaenderung anpassbar. | F104: Must | G104: 4 | H104: Design / Engineering | J104: Offen
A105: F-121 | B105: Progression | C105: Ausruestungsrang | D105: Rangstufen E bis S als Gate fuer Schwierigkeiten und Raids. Steigt durch Ausruestungsverbesserung. | E105: Rang wird korrekt berechnet und gated korrekt. | F105: Must | G105: 5 | H105: Design / Engineering | I105: F-122 | J105: Offen
A106: F-122 | B106: Progression | C106: Ausruestungs-Upgrades mit Budget | D106: Statt 8 unabhaengiger Statleitern ein gemeinsames Punktebudget mit Zielkonflikten: Tempo kostet Kontrolle, Schaden kostet Haltbarkeit. | E106: Es existiert kein dominanter Build; mindestens 4 Builds sind innerhalb 10 Prozent gleich stark. | F106: Must | G106: 10 | H106: Design / Engineering | I106: F-120 | J106: Offen
A107: F-123 | B107: Progression | C107: Faehigkeitenbaum | D107: Vier Aeste (Offensive, Defensive, Unterstuetzung, Traversal) mit exklusiven Knoten, die echte Entscheidungen erzwingen. | E107: Mindestens 12 Knoten sind gegenseitig exklusiv; nicht alles ist gleichzeitig freischaltbar. | F107: Must | G107: 12 | H107: Design / Engineering | I107: F-120 | J107: Offen
A108: F-124 | B108: Progression | C108: Kostenloser Respec | D108: Faehigkeitspunkte lassen sich mindestens einmal taeglich kostenlos neu verteilen. | E108: Respec ist ohne Waehrung nutzbar und im UI prominent. | F108: Must | G108: 3 | H108: Engineering | I108: F-123 | J108: Offen
A109: F-125 | B109: Progression | C109: Loadout-Speicher | D109: Mindestens fuenf frei benennbare Ausruestungs-Profile, kostenlos fuer alle Spieler. | E109: Wechsel zwischen Profilen dauert unter 1 s und ist im Hub jederzeit moeglich. | F109: Must | G109: 5 | H109: Engineering / UI | I109: F-123 | J109: Offen
A110: F-126 | B110: Progression | C110: Perk-System | D110: Vier gleichzeitig ausruestbare Perks in drei Kategorien. Fokus auf Synergien und Verhaltensaenderungen statt reiner Prozentwerte. | E110: Mindestens 40 Perks zu Release; mindestens 15 aendern Spielverhalten statt nur Zahlen. | F110: Must | G110: 10 | H110: Design / Engineering | I110: F-123 | J110: Offen
A111: F-127 | B111: Progression | C111: Lineage-System (Familien) | D111: Herkunftslinien mit aktiven Faehigkeiten. Jede Linie hat mindestens eine aktive Faehigkeit; es gibt keine leeren Linien. | E111: Kein Spieler kann eine Linie ohne Faehigkeit erhalten. | F111: Should | G111: 10 | H111: Design / Engineering | I111: F-126 | J111: Offen
A112: F-128 | B112: Progression | C112: Pity-System fuer Lineages | D112: Garantierte Seltenheitsstufen nach definierter Anzahl Ziehungen. Zaehler ist jederzeit sichtbar. | E112: Garantie greift exakt; Zaehler wird persistent gespeichert. | F112: Must | G112: 5 | H112: Design / Engineering | I112: F-127 | J112: Offen
A113: F-129 | B113: Progression | C113: Deterministischer Ichor-Pfad | D113: Vessel-Vials sind zusaetzlich ueber eine Raid-Waehrung garantiert erwerbbar. Zufallsdrop bleibt als Abkuerzung. | E113: Ein Spieler erreicht das Ziel nach definierter Anzahl Clears garantiert. | F113: Should | G113: 6 | H113: Design / Engineering | I113: F-105 | J113: Offen
A114: F-130 | B114: Progression | C114: Artefakte mit Substats | D114: Permanente Ausruestungsstuecke aus Raids und Erfolgen mit rerollbaren Nebenwerten und Sperrfunktion. | E114: Reroll und Sperre funktionieren; Kosten sind transparent. | F114: Could | G114: 9 | H114: Design / Engineering | I114: F-126 | J114: Offen
A115: F-131 | B115: Progression | C115: Ascension (Prestige-Ersatz) | D115: Zuruecksetzung nur der Build-Entscheidungen bei erweitertem Punktebudget. Mechanische Faehigkeiten und Ausruestungsraenge bleiben erhalten. | E115: Spieler wird nach Ascension nicht schwaecher, sondern flexibler. | F115: Should | G115: 8 | H115: Design / Engineering | I115: F-122 | J115: Offen
A116: F-132 | B116: Progression | C116: Memories (Ascension-Talente) | D116: Pro Ascension ein permanentes Talent aus drei Vorschlaegen. Neuwurf ueber Spielwaehrung, nicht ueber Echtgeld. | E116: Talente sind persistent; Auswahl ist rueckgaengig machbar bis zur Bestaetigung. | F116: Could | G116: 6 | H116: Design / Engineering | I116: F-131 | J116: Offen
A117: F-133 | B117: Progression | C117: Erfolge und Meilensteine | D117: Strukturierte Erfolgsliste mit Kategorien, Fortschrittsanzeige und Belohnungen (Waehrung, Kosmetik, Titel). | E117: Mindestens 120 Erfolge; alle mit sichtbarem Fortschritt. | F117: Should | G117: 7 | H117: Design / Engineering | J117: Offen
A118: F-134 | B118: Progression | C118: Kompendium | D118: Im Spiel einsehbare Datenbank: alle Formeln, Drop-Raten, Pity-Zaehler, Gegnerverhalten, Statwirkungen. | E118: Kein Spieler muss ein externes Wiki oeffnen, um eine Zahl zu erfahren. | F118: Should | G118: 8 | H118: Design / UI | I118: F-126 | J118: Offen
A119: F-135 | B119: Progression | C119: Build-Simulator im Hub | D119: Rechnerische Vorschau auf Schaden, Time-to-Kill und Traversal-Werte, ohne Ressourcen auszugeben. | E119: Vorschauwerte stimmen mit der Praxis auf 5 Prozent genau ueberein. | F119: Should | G119: 8 | H119: Engineering / UI | I119: F-134 | J119: Offen
A120: F-140 | B120: Oekonomie | C120: Zwei Waehrungen | D120: Weiche Waehrung (Mark) aus Missionen, harte Waehrung (Sigil) aus Erfolgen und Wochenzielen. Keine dritte Waehrung. | E120: Nur zwei Waehrungen existieren im gesamten Spiel. | F120: Must | G120: 4 | H120: Design / Engineering | J120: Offen
A121: F-141 | B121: Oekonomie | C121: Serverseitige Beutetabellen | D121: Alle Drops werden ausschliesslich auf dem Server bestimmt. Client erfaehrt nur das Ergebnis. | E121: Kein Client-Eingriff kann Drops beeinflussen. | F121: Must | G121: 6 | H121: Engineering | I121: F-140 | J121: Offen
A122: F-142 | B122: Oekonomie | C122: Pity-Zaehler fuer alle Seltenheiten | D122: Garantien ab Seltenheitsstufe Episch aufwaerts, pro Quelle getrennt gefuehrt und sichtbar. | E122: Zaehler werden persistiert und im Kompendium angezeigt. | F122: Must | G122: 5 | H122: Design / Engineering | I122: F-141 | J122: Offen
A123: F-143 | B123: Oekonomie | C123: Transparente Drop-Raten | D123: Alle Wahrscheinlichkeiten sind im Spiel einsehbar, inklusive Wirkung des Glueckswerts. | E123: Angezeigte Rate stimmt mit der tatsaechlichen Rate ueberein (Testabgleich ueber 10000 Rolls). | F123: Should | G123: 4 | H123: Design / Engineering | I123: F-134 | J123: Offen
A124: F-144 | B124: Oekonomie | C124: Glueckswert (Luck) | D124: Modifikator auf Drop-Raten mit dokumentierter, linearer Formel. Keine versteckten Multiplikatoren. | E124: Formel ist im Kompendium einsehbar und im Code identisch. | F124: Should | G124: 3 | H124: Design / Engineering | I124: F-143 | J124: Offen
A125: F-145 | B125: Oekonomie | C125: Automatischer Verkauf und Filter | D125: Regelbasierter Auto-Verkauf nach Seltenheit und Typ, kostenlos fuer alle. | E125: Filter funktioniert; kein Gamepass erforderlich. | F125: Must | G125: 5 | H125: Engineering / UI | I125: F-140 | J125: Offen
A126: F-146 | B126: Oekonomie | C126: Waehrungssenken | D126: Kosmetik, Neuwuerfe, Reparatur, Wochenkontingente. Keine Sackgasse, in der Waehrung wertlos wird. | E126: Auch ein Maximalspieler hat sinnvolle Ausgabemoeglichkeiten. | F126: Should | G126: 5 | H126: Design | I126: F-140 | J126: Offen
A127: F-147 | B127: Oekonomie | C127: Handelssystem | D127: Spielerhandel mit Steuer, Bestaetigungs-Countdown, vollstaendigem Handelsprotokoll und Rueckverfolgbarkeit. | E127: Kein Handel ist ohne beidseitige Bestaetigung abschliessbar; jeder Handel ist geloggt. | F127: Could | G127: 12 | H127: Engineering | I127: F-141 | J127: Offen
A128: F-148 | B128: Oekonomie | C128: Wochenkontingente statt AFK | D128: Belohnungen ueber taegliche und woechentliche Ziele statt ueber passives Herumstehen. | E128: Kein Vorteil durch Inaktivitaet im Spiel messbar. | F128: Should | G128: 5 | H128: Design / Engineering | I128: F-140 | J128: Offen
A129: F-150 | B129: Mehrspieler | C129: Sitzungsmodell | D129: Jede Mission und jeder Raid laeuft in einer eigenen reservierten Serverinstanz. Der Hub ist ein persistenter Treffpunkt, die Einsatzinstanz ist kurzlebig und wird nach Abschluss aufgeloest. | E129: Eine Instanz startet, laeuft und wird sauber abgebaut, ohne Spieler in einem toten Server zuruecklassen. | F129: Must | G129: 8 | H129: Engineering | I129: F-070 | J129: Offen
A130: F-151 | B130: Mehrspieler | C130: Serverkapazitaet | D130: Zielwerte: 20 Spieler pro Missionsinstanz, 10 pro Raidinstanz, 40 im Hub. Kapazitaet ist per Config je Modus einstellbar. | E130: Alle drei Kapazitaeten laufen im Lasttest bei 60 FPS auf dem PC-Mindestprofil. | F130: Must | G130: 5 | H130: Engineering | I130: F-150 | J130: Offen
A131: F-152 | B131: Mehrspieler | C131: Schnellsuche (Quick Play) | D131: Ein-Klick-Einstieg: das System sucht eine passende laufende oder startende Instanz nach Modus, Schwierigkeit und Ausruestungsrang. | E131: Ein Alleinspieler landet in unter 20 Sekunden in einer passenden Instanz. | F131: Must | G131: 8 | H131: Engineering | I131: F-150 | J131: Offen
A132: F-153 | B132: Mehrspieler | C132: Instanz-Browser | D132: Manuelle Auswahl laufender Instanzen mit Filter nach Map, Modus, Schwierigkeit, Modifikatoren, Spielerzahl und Freundesbeteiligung. Fuer Spieler, die nicht dem Automatismus folgen wollen. | E132: Filter kombinierbar; Liste aktualisiert sich alle 5 Sekunden ohne Ruckler. | F132: Should | G132: 9 | H132: Engineering / UI | I132: F-152 | J132: Offen
... A161: F-160 | B161: Sozial | C161: Bestenlisten | D161: Traversal-Zeiten pro Map, Raid-Clear-Zeiten, Saisonwertung. Getrennt nach Eingabegeraet. | E161: Listen sind serveruebergreifend und werden saisonal archiviert. | F161: Should | G161: 8 | H161: Engineering | I161: F-077 | J161: Offen
A162: F-170 | B162: UI | C162: HUD-Grundlayout | D162: Gas links, Klingen rechts, HP unten mittig, Ladeleiste, Nachladezaehler, Verletzungsanzeige, Zielfortschritt. | E162: Alle Werte sind ohne Menuewechsel ablesbar; HUD verdeckt nie die Bildmitte. | F162: Must | G162: 8 | H162: UI / Engineering | J162: Offen
...

Sheet 02_3D-Assets
A1: 02_3D-Assets
A2: Polygonbudgets sind Obergrenzen, keine Ziele. Wert 0 bedeutet: kein Mesh (Rig oder Texturvariante).
A4: ID | B4: Kategorie | C4: Asset | D4: Beschreibung | E4: Tris LOD0 | F4: Tris LOD1 | G4: Tris LOD2 | H4: Varianten | I4: Textur-Slot | J4: Prio | K4: Aufwand (PT) | L4: Status
A5: A-001 | B5: Charakter | C5: Basis-Rig Vanguard | D5: Humanoides R15-kompatibles Grundskelett fuer alle Spielerfiguren. Zusaetzliche Knochen: 6 fuer Umhang, 2 pro Gurtriemen, 4 fuer Vector-Gear-Seile. | E5: 0 | F5: 0 | G5: 0 | H5: 1 | I5: - | J5: Must | K5: 5 | L5: Offen
A6: A-002 | B6: Charakter | C6: Koerper maennlich schlank | D6: Low-Poly-Grundkoerper, kantige Silhouette, klare Schulterlinie fuer gute Lesbarkeit aus der Distanz. | E6: 1400 | F6: 700 | G6: 300 | H6: 1 | I6: TEX-CHAR-01 | J6: Must | K6: 3 | L6: Offen
A7: A-003 | B7: Charakter | C7: Koerper weiblich schlank | D7: Gleiches Polybudget, abweichende Proportionen, identische Rig-Kompatibilitaet. | E7: 1400 | F7: 700 | G7: 300 | H7: 1 | I7: TEX-CHAR-01 | J7: Must | K7: 3 | L7: Offen
A8: A-004 | B8: Charakter | C8: Koerper kraeftig | D8: Dritte Statur-Variante fuer Kundenvielfalt in der Charaktererstellung. | E8: 1500 | F8: 750 | G8: 300 | H8: 1 | I8: TEX-CHAR-01 | J8: Should | K8: 3 | L8: Offen
A9: A-005 | B9: Charakter | C9: Kopf-Basis | D9: Vier Kopfformen (kantig, rund, schmal, breit) als austauschbare Meshes. | E9: 400 | F9: 200 | G9: 80 | H9: 4 | I9: TEX-CHAR-01 | J9: Must | K9: 4 | L9: Offen
A10: A-006 | B10: Charakter | C10: Frisuren | D10: Zwoelf Low-Poly-Frisuren als Kappengeometrie, farbkanalfaehig. Keine Alphakanten. | E10: 250 | F10: 120 | G10: 50 | H10: 12 | I10: TEX-CHAR-01 | J10: Must | K10: 8 | L10: Offen
A11: A-007 | B11: Charakter | C11: Gesichtszuege | D11: Als Textur-Varianten auf dem Kopf-Atlas: 10 Augenformen, 6 Mundformen, 8 Narben/Marken. | E11: 0 | F11: 0 | G11: 0 | H11: 24 | I11: TEX-CHAR-01 | J11: Should | K11: 4 | L11: Offen
A12: A-008 | B12: Charakter | C12: Uniform Rekrut | D12: Einfache Feldkleidung ohne Abzeichen, gedeckte Farben. Startausruestung. | E12: 900 | F12: 450 | G12: 180 | H12: 1 | I12: TEX-CHAR-02 | J12: Must | K12: 4 | L12: Offen
A13: A-009 | B13: Charakter | C13: Uniform Vanguard | D13: Standarduniform mit Gurtwerk, Taschen und Rangabzeichen. Drei Farbkanaele. | E13: 1200 | F13: 600 | G13: 240 | H13: 1 | I13: TEX-CHAR-02 | J13: Must | K13: 5 | L13: Offen
A14: A-010 | B14: Charakter | C14: Uniform Elite | D14: Endgame-Uniform mit zusaetzlichem Schulterschutz und Verstaerkungen. | E14: 1400 | F14: 700 | G14: 280 | H14: 1 | I14: TEX-CHAR-02 | J14: Should | K14: 5 | L14: Offen
A15: A-011 | B15: Charakter | C15: Umhang Standard | D15: Umhang mit Knochenkette fuer prozedurale Bewegung. Musterflaeche als Kosmetik-Slot. | E15: 600 | F15: 300 | G15: 100 | H15: 1 | I15: TEX-CHAR-03 | J15: Must | K15: 5 | L15: Offen
A16: A-012 | B16: Charakter | C16: Umhang-Varianten | D16: Acht Schnittvarianten (kurz, lang, zerrissen, Kapuze, geteilt, Schulterumhang, Wintervariante, zeremoniell). | E16: 600 | F16: 300 | G16: 100 | H16: 8 | I16: TEX-CHAR-03 | J16: Could | K16: 6 | L16: Offen
... A104: A-153 | B104: Hub | C104: Sozialflaeche | D104: Innenhof mit Sitzgelegenheiten, Feuerstelle und Emote-Zonen. | E104: 1200 | F104: 600 | G104: 0 | H104: 1 | I104: TEX-ENV-ATLAS | J104: Should | K104: 5 | L104: Offen

Sheet 03_Animationen
A1: 03_Animationen
A2: Dauer 0 bedeutet: Sammelposten aus mehreren Clips (Moveset). Groesster unterschaetzter Aufwandsblock im Projekt.
A4: ID | B4: Rig | C4: Clip | D4: Beschreibung | E4: Dauer (s) | F4: Loop | G4: Prio | H4: Aufwand (PT) | I4: Status
A5: AN-001 | B5: Vanguard | C5: Idle | D5: Ruhige Standhaltung mit leichter Atmung und gelegentlichem Blick zur Seite. | E5: 4 | F5: Ja | G5: Must | H5: 1 | I5: Offen
A6: AN-002 | B6: Vanguard | C6: Idle angespannt | D6: Kampfbereite Haltung mit gezogenen Klingen, ausgeloest bei Titanen in Naehe. | E6: 4 | F6: Ja | G6: Must | H6: 1 | I6: Offen
A7: AN-003 | B7: Vanguard | C7: Walk | D7: Normales Gehen, alle acht Richtungen ueber Blending. | E7: 1 | F7: Ja | G7: Must | H7: 2 | I7: Offen
A8: AN-004 | B8: Vanguard | C8: Run | D8: Laufzyklus, alle acht Richtungen. | E8: 0.7 | F8: Ja | G8: Must | H8: 2 | I8: Offen
A9: AN-005 | B9: Vanguard | C9: Sprint | D9: Schneller Sprint mit vorgebeugter Haltung. | E9: 0.6 | F9: Ja | G9: Must | H9: 1 | I9: Offen
A10: AN-006 | B10: Vanguard | C10: Jump Start | D10: Absprung vom Boden. | E10: 0.4 | F10: Nein | G10: Must | H10: 1 | I10: Offen
A11: AN-007 | B11: Vanguard | C11: Fall | D11: Freier Fall ohne Haken, rudernde Arme, Panikhaltung. | E11: 1 | F11: Ja | G11: Must | H11: 1 | I11: Offen
A12: AN-008 | B12: Vanguard | C12: Land soft | D12: Weiche Landung aus geringer Hoehe, direkt in Locomotion uebergehend. | E12: 0.4 | F12: Nein | G12: Must | H12: 1 | I12: Offen
A13: AN-009 | B13: Vanguard | C13: Land hard | D13: Harte Landung mit Abrollen, kurze Kontrollsperre. | E13: 0.9 | F13: Nein | G13: Must | H13: 1 | I13: Offen
A14: AN-010 | B14: Vanguard | C14: Slide | D14: Bodengleiten mit ausgestrecktem Bein, I-Frame-Fenster. | E14: 0.8 | F14: Nein | G14: Must | H14: 2 | I14: Offen
A15: AN-011 | B15: Vanguard | C15: Stumble | D15: Straucheln nach Kollision, Uebergang in Recovery. | E15: 0.7 | F15: Nein | G15: Must | H15: 1 | I15: Offen
A16: AN-012 | B16: Vanguard | C16: Death | D16: Tod durch Titanenangriff, drei Varianten (zerquetscht, gefressen, Sturz). | E16: 2 | F16: Nein | G16: Must | H16: 3 | I16: Offen
... A104: AN-132 | B104: NPC Haendler | C104: Idle | D104: Standanimationen fuer Hub-NPCs, sechs Varianten. | E104: 5 | F104: Ja | G104: Should | H104: 3 | I104: Offen

Sheet 04_Texturen
A1: 04_Texturen
A2: Low-Poly-Grundsatz: Farbe statt Detail. Ein Umgebungsatlas fuer alle Kits, keine PBR-Maps.
A4: ID | B4: Name | C4: Aufloesung | D4: Typ | E4: Beschreibung | F4: Prio | G4: Status
A5: TEX-ENV-ATLAS | B5: Umgebungs-Palettenatlas | C5: 512x512 | D5: Albedo | E5: Zentraler Farbatlas fuer saemtliche Umgebungs-Assets. Alle Kits mappen ausschliesslich hierauf. Ergebnis: ein Material, minimale Drawcalls, garantierte Farbkonsistenz. | F5: Must | G5: Offen
A6: TEX-ENV-ATLAS-N | B6: Umgebungs-Normalmap | C6: 512x512 | D6: Normal | E6: Optionale, sehr flache Normalmap fuer Steinstruktur. Nur auf hoher Qualitaetsstufe geladen. | F6: Could | G6: Offen
A7: TEX-CHAR-01 | B7: Charakter-Haut und Haar | C7: 512x512 | D7: Albedo | E7: Hauttoene, Haarfarben, Gesichtszuege als Atlasfelder. Farbmodulation ersetzt zusaetzliche Texturen. | F7: Must | G7: Offen
A8: TEX-CHAR-02 | B8: Uniform-Atlas | C8: 512x512 | D8: Albedo | E8: Alle drei Uniformsets, Stiefel, Handschuhe, Gurtwerk. Drei tintbare Kanaele ueber Graustufenmasken. | F8: Must | G8: Offen
A9: TEX-CHAR-03 | B9: Umhang-Atlas | C9: 512x512 | D9: Albedo | E9: Umhangstoffe und Emblemflaechen. Emblembereich ist ein eigener UV-Bereich fuer Kosmetik. | F9: Must | G9: Offen
A10: TEX-GEAR-01 | B10: Vector-Gear-Atlas | C10: 512x512 | D10: Albedo | E10: Alle drei Geraetestufen, Klingen, Kanister, Haken, Lanzen. Metall ueber Farbwert, nicht ueber PBR. | F10: Must | G10: Offen
A11: TEX-GEAR-02 | B11: Kosmetik-Klingen | C11: 512x512 | D11: Albedo | E11: Zwoelf Klingenvarianten fuer den Shop. | F11: Could | G11: Offen
A12: TEX-TITAN-01 | B12: Titan-Haut | C12: 512x512 | D12: Albedo | E12: Hauttoene und Muskelzeichnung fuer alle Pure-Titan-Typen. Varianz ueber Farbmodulation statt neuer Texturen. | F12: Must | G12: Offen
A13: TEX-TITAN-02 | B13: Titan-Wunden | C13: 512x512 | D13: Albedo + Emissiv | E13: Schnittflaechen, Dampfzonen und der leuchtende Cortex. Emissiver Kanal fuer Sichtbarkeit auf Distanz. | F13: Must | G13: Offen
A14: TEX-BOSS-01 | B14: The Bound One | C14: 1024x1024 | D14: Albedo | E14: Eigene Textur, da Boss im Nahbild praesentiert wird. | F14: Should | G14: Offen
A15: TEX-BOSS-02 | B15: The Dancer | C15: 1024x1024 | D15: Albedo | E15: Inklusive markierter Schwachstellenzonen. | F15: Should | G15: Offen
... A18: TEX-VESSEL-01 | B18: Warbound | C18: 1024x1024 | D18: Albedo | E18: Spielerform, im Nahbild sichtbar. | F18: Should | G18: Offen
A19: TEX-VESSEL-02 | B19: Bladewright | C19: 1024x1024 | D19: Albedo | F19: Could | G19: Offen
A20: TEX-VESSEL-03 | B20: Bulwark Form | C20: 1024x1024 | D20: Albedo | F20: Could | G20: Offen
A21: TEX-VESSEL-04 | B21: Colossus Form | C21: 1024x1024 | D21: Albedo + Emissiv | F21: Could | G21: Offen
A22: TEX-PROP-01 | B22: Prop-Atlas | C22: 512x512 | D22: Albedo | E22: Alle Requisiten, Nachschubstationen, Karren, Truhen. | F22: Must | G22: Offen
A23: TEX-VFX-01 | B23: Rauch- und Dampf-Flipbook | C23: 1024x1024 | D23: Flipbook 8x8 | E23: Rauch, Dampf, Titanenaufloesung. Ein Sheet fuer alle weichen Partikel. | F23: Must | G23: Offen
A24: TEX-VFX-02 | B24: Funken und Explosion | C24: 1024x1024 | D24: Flipbook 8x8 | E24: Explosionen, Funken, Aufprallblitze. | F24: Should | G24: Offen
A25: TEX-VFX-03 | B25: Trails und Streifen | C25: 256x256 | D25: Albedo | E25: Klingen-Trails, Speedlines, Seiltextur mit Scroll-Offset. | F25: Must | G25: Offen
A26: TEX-UI-01 | B26: UI-Atlas Kern | C26: 1024x1024 | D26: Albedo | E26: HUD-Elemente, Leisten, Rahmen und saemtliche Ankermarker-Sprites in ihren vier Zustaenden. Marker sind formverschieden, nicht nur farbverschieden. | F26: Must | G26: Offen
A27: TEX-UI-02 | B27: UI-Atlas Icons | C27: 1024x1024 | D27: Albedo | E27: Perk-, Skill-, Item- und Waehrungs-Icons. Mindestens 200 Symbole. | F27: Must | G27: Offen
A28: TEX-UI-03 | B28: UI-Atlas Menue | C28: 1024x1024 | D28: Albedo | E28: Menuehintergruende, Kartenmaterial, Zierelemente. | F28: Should | G28: Offen
A29: TEX-SKY-01 | B29: Himmel Tag | C29: Cubemap | D29: Skybox | E29: Klarer Tageshimmel mit hohen Wolken. | F29: Must | G29: Offen
A30: TEX-SKY-02 | B30: Himmel Daemmerung | C30: Cubemap | D30: Skybox | E30: Warme Abendstimmung, Standard fuer die Stadtmaps. | F30: Must | G30: Offen
A31: TEX-SKY-03 | B31: Himmel Nacht | C31: Cubemap | D31: Skybox | E31: Fuer Nacht-Modifikator. | F31: Should | G31: Offen
A32: TEX-SKY-04 | B32: Himmel Sturm | C32: Cubemap | D32: Skybox | E32: Fuer Regen-Modifikator mit reduzierter Sicht. | F32: Should | G32: Offen

Sheet 05_VFX
A1: 05_VFX
A3: ID | B3: Name | C3: Beschreibung | D3: Technik | E3: Ausloeser | F3: Prio | G3: Status
A4: VFX-001 | B4: Gasausstoss | C4: Weisser Dampfstrahl aus den Duesen des Vector Gear, Intensitaet skaliert mit Verbrauch. Kernfeedback fuer Geschwindigkeit. | D4: ParticleEmitter + Beam | E4: Boost, Dash, Reel-In | F4: Must | G4: Offen
A5: VFX-002 | B5: Gas-Restwarnung | C5: Stotternder, ausduennender Ausstoss bei unter 15 Prozent Gas. | D5: ParticleEmitter | E5: Gas niedrig | F5: Must | G5: Offen
A6: VFX-003 | B6: Seilvisualisierung | C6: Ankerseil als Beam mit scrollender Textur und leichtem Durchhang. | D6: Beam | E6: Haken aktiv | F6: Must | G6: Offen
A7: VFX-004 | B7: Hakeneinschlag | C7: Materialabhaengiger Aufprall: Steinsplitter, Holzspaene, Blutdampf. | D7: ParticleEmitter | E7: Haken trifft | F7: Must | G7: Offen
A8: VFX-005 | B8: Speedlines | C8: Radiale Streifen am Bildrand ab definierter Geschwindigkeit. | D8: ScreenGui + Bildschirmeffekt | E8: Velocity-Schwelle | F8: Must | G8: Offen
A9: VFX-006 | B9: Geschwindigkeits-Vignette | C9: Randabdunklung und Chromatische Aberration bei Hoechsttempo. Abschaltbar. | D9: PostEffect | E9: Velocity-Schwelle | F9: Should | G9: Offen
A10: VFX-007 | B10: Klingen-Trail | C10: Nachziehende Schneidspur, Farbe als Kosmetik-Slot. | D10: Trail | E10: Klingenangriff | F10: Must | G10: Offen
A11: VFX-008 | B11: Cortex-Schnitt | C11: Dampf- und Blutschwaden aus der Schnittwunde, kein realistisches Blut. | D11: ParticleEmitter | E11: Cortex-Treffer | F11: Must | G11: Offen
A12: VFX-009 | B12: Gliedmassen-Schnitt | C12: Kleinere Dampfwolke an Arm- oder Beinwunde plus abfallendes Mesh. | D12: ParticleEmitter | E12: Gliedmassentreffer | F12: Must | G12: Offen
A13: VFX-010 | B13: Titan-Aufloesung | C13: Aufsteigende Dampfsaeule und schwindendes Mesh ueber 3 Sekunden. | D13: ParticleEmitter + Transparenzkurve | E13: Titan-Tod | F13: Must | G13: Offen
A14: VFX-011 | B14: Cortex-Markierung | C14: Sanftes Pulsieren des Nackenbereichs, aus Distanz sichtbar. | D14: Emissive + Pulskurve | E14: Titan aktiv | F14: Must | G14: Offen
... A42: VFX-039 | B42: Fehlversuch-Rueckzug | C42: Ins Leere gefeuerter Haken mit sichtbarem Seilrueckzug statt stillem Nichtereignis. | D42: Beam + Trail | E42: Kein gueltiges Ziel | F42: Must | G42: Offen

Sheet 06_Audio
A1: 06_Audio
A2: Musik muss original oder lizenziert sein. Anime-Soundtracks sind auf Roblox nicht hochladbar.
A4: ID | B4: Kategorie | C4: Name | D4: Beschreibung | E4: Laenge | F4: Loop | G4: Prio | H4: Status
A5: S-001 | B5: Vector Gear | C5: Hook Fire | D5: Druckluftartiger Abschussknall des Ankerwerfers, kurz und trocken. Zwei Varianten fuer links und rechts. | E5: 0.4s | F5: Nein | G5: Must | H5: Offen
A6: S-002 | B6: Vector Gear | C6: Hook Impact Stein | D6: Metallischer Einschlag in Mauerwerk mit kurzem Nachhall. | E6: 0.5s | F6: Nein | G6: Must | H6: Offen
A7: S-003 | B7: Vector Gear | C7: Hook Impact Holz | D7: Dumpferer, hoelzerner Einschlag. | E7: 0.5s | F7: Nein | G7: Must | H7: Offen
A8: S-004 | B8: Vector Gear | C8: Hook Impact Fleisch | D8: Feuchter, unangenehmer Einschlag in Titanenkoerper. | E8: 0.5s | F8: Nein | G8: Must | H8: Offen
A9: S-005 | B9: Vector Gear | C9: Hook Miss | D9: Ins Leere gehender Haken, Seilrasseln und Rueckzug. | E9: 0.8s | F9: Nein | G9: Must | H9: Offen
A10: S-006 | B10: Vector Gear | C10: Seileinzug | D10: Ratterndes Aufrollen der Winde, Tonhoehe skaliert mit Einzuggeschwindigkeit. | E10: 2.0s | F10: Ja | G10: Must | H10: Offen
A11: S-007 | B11: Vector Gear | C11: Gas-Zischen | D11: Der Signature-Sound des Genres. Kontinuierlicher Druckluftstrom, Lautstaerke und Tonhoehe an Boost gekoppelt. | E11: 3.0s | F11: Ja | G11: Must | H11: Offen
A12: S-008 | B12: Vector Gear | C12: Gas-Dash | D12: Kurzer, harter Druckstoss mit Bassanteil. | E12: 0.4s | F12: Nein | G12: Must | H12: Offen
A13: S-009 | B13: Vector Gear | C13: Gas leer Warnung | D13: Stotterndes Zischen plus subtiler Warnton, nicht aufdringlich. | E13: 1.0s | F13: Nein | G13: Must | H13: Offen
A14: S-010 | B14: Vector Gear | C14: Hook Release | D14: Metallisches Klacken beim Loesen. | E14: 0.2s | F14: Nein | G14: Must | H14: Offen
A15: S-011 | B15: Vector Gear | C15: Hook Break | D15: Doppelter Abschuss nach hinten mit abruptem Spannungsgeraeusch. | E15: 0.7s | F15: Nein | G15: Should | H15: Offen
... A122: MU-012 | B122: Musik | C122: Saison-Thema | D122: Ein zusaetzliches Stueck pro Saison zur Wiedererkennung. | E122: 150s | F122: Ja | G122: Could | H122: Offen

Sheet 07_UI-Screens
A1: 07_UI-Screens
A3: ID | B3: Screen | C3: Beschreibung | D3: Wichtigste Elemente | E3: Plattform | F3: Prio | G3: Aufwand (PT) | H3: Status
A4: UI-001 | B4: Startbildschirm | C4: Erster Bildschirm nach dem Laden. Spielemblem, Neuigkeiten, Einstieg. | D4: Play, Neuigkeiten, Einstellungen, Sozial-Links | E4: PC | F4: Must | G4: 3 | H4: Offen
A5: UI-002 | B5: Charaktererstellung | C5: Aufbau der Spielfigur mit Vorschau in Echtzeit. | D5: Statur, Kopf, Frisur, Gesicht, Farben, Name | E5: PC | F5: Must | G5: 10 | H5: Offen
A6: UI-003 | B6: Profil-Slots | C6: Verwaltung mehrerer Charaktere. | D6: Slot-Liste, Erstellen, Loeschen, Vorschau | E6: PC | F6: Should | G6: 4 | H6: Offen
A7: UI-004 | B7: Haupt-HUD | C7: Kern-Overlay im Einsatz. | D7: Gas, Klingen, HP, Ladeleiste, Nachladezaehler, Verletzungen, Zielfortschritt, Minikarte | E7: PC | F7: Must | G7: 12 | H7: Offen
A8: UI-005 | B8: Fadenkreuz und Ankermarker | C8: Dynamische Zielanzeige plus die eingeblendeten Ankermarker im Sichtfeld. Kern der Traversal-Lesbarkeit: der Spieler muss jederzeit ohne Nachdenken wissen, wohin Q und E ihn bringen. | D8: Fadenkreuz-Zustaende, Ankermarker in 4 Zustaenden, Q/E-Tastensymbole, Reichweitenanzeige, Cortex-Erkennung, Dichtebegrenzung | E8: PC | F8: Must | G8: 9 | H8: Offen
A9: UI-038 | B9: Ankermarker-Einstellungen | C9: Konfiguration der Traversal-Hilfen. Getrennt von den allgemeinen Einstellungen, weil hier die Balance zwischen Zugaenglichkeit und Meisterschaft geregelt wird. | D9: Zielmodus (Frei/Assistiert/Snap), Fangwinkel-Regler, Marker-Deckkraft, maximale Markeranzahl, Vollabschaltung, Vorschaufenster | E9: PC | F9: Must | G9: 6 | H9: Offen
A10: UI-006 | B10: Einsatzkarte | C10: Missionsauswahl mit Map, Modus, Schwierigkeit und Modifikatoren. | D10: Kartenansicht, Modusfilter, Schwierigkeitswahl, Modifikatorliste, Belohnungsvorschau | E10: PC | F10: Must | G10: 12 | H10: Offen
A11: UI-007 | B11: Ausruestung | C11: Verwaltung von Vector Gear, Klingen und Lanzen. | D11: Upgrade-Budget, Statvorschau, Zielkonfliktanzeige | E11: PC | F11: Must | G11: 10 | H11: Offen
A12: UI-008 | B12: Faehigkeitenbaum | C12: Interaktiver Baum mit vier Aesten. | D12: Knoten, Verbindungen, exklusive Pfade, Respec-Button, Punktezaehler | E12: PC | F12: Must | G12: 14 | H12: Offen
A13: UI-009 | B13: Perk-Verwaltung | C13: Ausruesten und Vergleichen von Perks. | D13: Vier Slots, Perk-Inventar, Filter, Vergleichsansicht | E13: PC | F13: Must | G13: 8 | H13: Offen
A14: UI-010 | B14: Lineage-Halle | C14: Herkunftslinien, Ziehungen und Pity-Anzeige. | D14: Aktuelle Linie, Ziehung, Pity-Zaehler, Sammlungsuebersicht | E14: PC | F14: Should | G14: 8 | H14: Offen
A15: UI-011 | B15: Loadout-Verwaltung | C15: Speichern und Wechseln von Build-Profilen. | D15: Fuenf Slots, Benennung, Schnellwechsel | E15: PC | F15: Must | G15: 5 | H15: Offen
... A48: UI-037 | B48: Zuschauermodus | C48: Beobachtungsoberflaeche. | D48: Spielerwechsel, Kameramodi, HUD-Umschaltung | E48: PC | F48: Could | G48: 5 | H48: Offen

Sheet 08_Maps
A1: 08_Maps
A2: Ankerdichte ist die wichtigste Leveldesign-Variable: sie bestimmt die Schwierigkeit der Traversal.
A4: ID | B4: Map | C4: Beschreibung | D4: Unterstuetzte Modi | E4: Groesse (studs) | F4: Ankerdichte | G4: Prio | H4: Aufwand (PT) | I4: Status
A5: M-001 | B5: The Rookery (Hub) | C5: Zentrale Basis im Inneren der Bastionsmauer. Innenhof, Werkstatt, Lineage-Halle, Haendler, Medic, Einsatzkarte, Bestenlisten, Trainingsgelaende. Keine Gegner. | D5: Hub | E5: 1200x1200 | F5: Hoch | G5: Must | H5: 25 | I5: Offen
A6: M-002 | B6: Ashgate District | C6: Enge Altstadt mit Fachwerk, Kanaelen und schmalen Gassen. Hoechste Ankerdichte, belohnt praezises Manoevrieren. Einsteigermap. | D6: Skirmish, Breach, Randomizer, Traversal | E6: 2000x2000 | F6: Sehr hoch | G6: Must | H6: 30 | I6: Offen
A7: M-003 | B7: Brackwall | C7: Weitraeumige Neustadt mit breiten Boulevards und Plaetzen. Weniger Anker, mehr Boost-Bedarf. Lehrt Gasmanagement. | D7: Skirmish, Protect, Randomizer, Traversal | E7: 2400x2400 | F7: Mittel | G7: Must | H7: 28 | I7: Offen
A8: M-004 | B8: The Fallow | C8: Offenes Feld mit Baumgruppen, Ruinen und einer Handelsstrasse. Gefaehrlichste Map fuer Anfaenger wegen fehlender Anker. | D8: Escort, Skirmish, Randomizer | E8: 3000x3000 | F8: Niedrig | G8: Must | H8: 26 | I8: Offen
A9: M-005 | B9: Titanwood | C9: Wald mit Riesenbaeumen. Vertikale Kampffuehrung, dichte Deckung, eingeschraenkte Sicht. Beliebteste Maparchitektur des Genres. | D9: Skirmish, Protect, Reclaim, Traversal | E9: 2600x2600 | F9: Sehr hoch | G9: Must | H9: 30 | I9: Offen
A10: M-006 | B10: Hollowkeep | C10: Isolierte Festung im Oedland, umgeben von Freiflaeche. Verteidigungsszenario mit begrenztem Rueckzugsraum. | D10: Breach, Stall, Reclaim | E10: 1800x1800 | F10: Mittel | G10: Should | H10: 24 | I10: Offen
A11: M-007 | B11: Saltpier | C11: Hafenanlage mit Lagerhaeusern, Kraenen und Kaimauern. Mehrgeschossige Innenraeume, ungewoehnliche Ankerhoehen. | D11: Stall, Skirmish, Reclaim | E11: 2200x2200 | F11: Hoch | G11: Should | H11: 26 | I11: Offen
A12: M-008 | B12: Highspire | C12: Wohlhabender Oberstadtbezirk mit hohen Steinbauten und Saeulenhallen. Vertikalste Stadtmap. | D12: Skirmish, Protect, Randomizer, Traversal | E12: 2000x2400 | F12: Hoch | G12: Should | H12: 26 | I12: Offen
A13: M-009 | B13: The Breach (Raid) | C13: Mauerabschnitt mit Bresche und Kanonenplattformen. Speziell fuer den Ashwalker-Raid gebaut. | D13: Raid | E13: 1600x1600 | F13: Mittel | G13: Should | H13: 22 | I13: Offen
A14: M-010 | B14: The Hollow (Raid) | C14: Amphitheaterartige Senke fuer Bosskaempfe mit klaren Sichtlinien und Ankerpfeilern. | D14: Raid | E14: 1200x1200 | F14: Hoch | G14: Should | H14: 20 | I14: Offen
A15: M-011 | B15: Trainingsgelaende | C15: Teil des Hubs. Parcoursringe, bewegliche Ziele, Zeitmessung, Uebungstitanen aller Typen. | D15: Tutorial, Uebung | E15: 800x800 | F15: Sehr hoch | G15: Must | H15: 14 | I15: Offen
A16: M-012 | B16: Trade Hall | C16: Separater Handelsraum mit Handelsplaetzen und Marktbrett. | D16: Handel | E16: 400x400 | F16: Niedrig | G16: Could | H16: 8 | I16: Offen

Sheet 09_Tech-Backlog
A1: 09_Tech-Backlog
A3: ID | B3: Modul | C3: Task | D3: Beschreibung | E3: Rolle | F3: Prio | G3: Aufwand (PT) | H3: Status
A4: T-001 | B4: Projekt | C4: Rojo- und Git-Aufsetzung | D4: Externes Dateisystem mit Versionierung. Bei dieser Projektgroesse zwingend; Arbeiten allein in Studio ist ausgeschlossen. | E4: Tech Lead | F4: Must | G4: 3 | H4: Offen
A5: T-002 | B5: Projekt | C5: Branch- und Review-Prozess | D5: Feature-Branches, Pull Requests, verpflichtende Code-Reviews, Namenskonventionen. | E5: Tech Lead | F5: Must | G5: 2 | H5: Offen
A6: T-003 | B6: Projekt | C6: Service-Framework | D6: Schlankes eigenes Framework oder Knit. Einheitliche Lebenszyklen fuer alle Dienste. | E6: Tech Lead | F6: Must | G6: 6 | H6: Offen
A7: T-004 | B7: Projekt | C7: Luau strict mode | D7: Durchgaengige Typannotationen in allen Modulen, Linting in der Pipeline. | E7: Tech Lead | F7: Must | G7: 4 | H7: Offen
A8: T-005 | B8: Projekt | C8: Konfigurationsschicht | D8: Alle Balancing-Werte in reinen Datenmodulen ohne Logik, von Designern editierbar. | E8: Engineering | F8: Must | G8: 5 | H8: Offen
A9: T-006 | B9: Projekt | C9: Testumgebung | D9: Separates Universe fuer Tests mit eigenem Datastore-Scope und Testkonten. | E9: Tech Lead | F9: Must | G9: 4 | H9: Offen
A10: T-007 | B10: Projekt | C10: Automatisierte Smoke-Tests | D10: Skriptgesteuerter Start jeder Map mit Pruefung auf Fehler in der Ausgabe. | E10: Engineering | F10: Should | G10: 6 | H10: Offen
A11: T-010 | B11: Netzwerk | C11: Remote-Bundling | D11: Alle RemoteEvents ueber eine zentrale, typisierte Schicht mit Rate-Limiting und Validierung. | E11: Engineering | F11: Must | G11: 6 | H11: Offen
A12: T-011 | B12: Netzwerk | C12: Client-Prediction | D12: Lokale Vorhersage der eigenen Bewegung mit Server-Abgleich und weicher Korrektur. | E12: Engineering | F12: Must | G12: 12 | H12: Offen
A13: T-012 | B13: Netzwerk | C13: Replikationsdrosselung | D13: Titanenzustaende nur an Clients in Relevanzradius senden; Interpolation clientseitig. | E13: Engineering | F13: Must | G13: 8 | H13: Offen
A14: T-013 | B14: Netzwerk | C14: Latenzkompensation | D14: Trefferpruefung mit Ruecksicht auf die Latenz des Angreifers, mit Obergrenze. | E14: Engineering | F14: Should | G14: 8 | H14: Offen
A15: T-014 | B15: Netzwerk | C15: Instanzverwaltung | D15: Reservierte Server pro Einsatz, Lebenszyklus vom Start bis zum sauberen Abbau, Wiederverwendung leerer Instanzen. | E15: Engineering | F15: Must | G15: 10 | H15: Offen
... A54: T-074 | B54: QA | C54: Playtest-Protokoll | D54: Standardisierter Ablauf fuer Blindtests inklusive Fragebogen und Metriken. | E54: QA / Design | F54: Must | G54: 4 | H54: Offen

Sheet 10_Namensschema
A1: 10_Namensschema
A2: Eigene Begriffswelt. Verbindlich fuer Code, Assets, UI-Texte und Dokumentation.
A4: Referenzbegriff | B4: Defeated by Titan | C4: Anmerkung
A5: Attack on Titan Revolution | B5: Defeated by Titan | C5: Projekttitel
A6: Titan | B6: Titan | C6: Gattungsbegriff, bleibt
A7: ODM Gear / 3DMG | B7: Vector Gear (VG) | C7: Kernausruestung; im Deutschen Vektorgeschirr
A8: Nape / Nacken | B8: Cortex | C8: Einziger Kill-Punkt; eigener, praegnanter Begriff
A9: Thunder Spear | B9: Lance Charge | C9: Explosive Fernwaffe
A10: Survey Corps / Scouts | B10: The Vanguard | C10: Spielerfraktion
A11: Soldat / Recruit | B11: Vanguard | C11: Spielerbezeichnung
A12: Titan Shifting | B12: Bonding | C12: Verwandlungsmechanik
A13: Shifter-Form | B13: Vessel Form | C13: Spielbare Titanenform
A14: Titan Serum | B14: Ichor Vial | C14: Freischaltgegenstand fuer Vessel Forms
A15: Family / Clan | B15: Lineage | C15: Herkunftslinie mit Faehigkeiten
... A44: Regiment / Guild | B44: Regiment | C44: Bleibt, generischer Begriff

Sheet 11_Zusammenfassung
A1: Zusammenfassung
A2: Alle Werte sind Formeln und aktualisieren sich, wenn Zeilen ergaenzt oder Prioritaeten geaendert werden.
A4: Blatt | B4: Eintraege | C4: Must | D4: Should | E4: Could | F4: Aufwand (PT)
A5: 01_Spielfunktionen | B5: =COUNTA(01_Spielfunktionen!A5:A198) -> 194 | C5: =COUNTIF(01_Spielfunktionen!F5:F198,"Must") -> 99 | D5: =COUNTIF(01_Spielfunktionen!F5:F198,"Should") -> 71 | E5: =COUNTIF(01_Spielfunktionen!F5:F198,"Could") -> 24 | F5: =SUM(01_Spielfunktionen!G5:G198) -> 1328
A6: 02_3D-Assets | B6: =COUNTA('02_3D-Assets'!A5:A104) -> 100 | C6: =COUNTIF('02_3D-Assets'!J5:J104,"Must") -> 42 | D6: =COUNTIF('02_3D-Assets'!J5:J104,"Should") -> 50 | E6: =COUNTIF('02_3D-Assets'!J5:J104,"Could") -> 8 | F6: =SUM('02_3D-Assets'!K5:K104) -> 477
A7: 03_Animationen | B7: =COUNTA(03_Animationen!A5:A104) -> 100 | C7: =COUNTIF(03_Animationen!G5:G104,"Must") -> 59 | D7: =COUNTIF(03_Animationen!G5:G104,"Should") -> 32 | E7: =COUNTIF(03_Animationen!G5:G104,"Could") -> 9 | F7: =SUM(03_Animationen!H5:H104) -> 270
A8: 04_Texturen | B8: =COUNTA(04_Texturen!A5:A32) -> 28 | C8: =COUNTIF(04_Texturen!F5:F32,"Must") -> 14 | D8: =COUNTIF(04_Texturen!F5:F32,"Should") -> 9 | E8: =COUNTIF(04_Texturen!F5:F32,"Could") -> 5 | F8: -
A9: 05_VFX | B9: =COUNTA(05_VFX!A4:A42) -> 39 | C9: =COUNTIF(05_VFX!F4:F42,"Must") -> 15 | D9: =COUNTIF(05_VFX!F4:F42,"Should") -> 22 | E9: =COUNTIF(05_VFX!F4:F42,"Could") -> 2 | F9: -
A10: 06_Audio | B10: =COUNTA(06_Audio!A5:A122) -> 118 | C10: =COUNTIF(06_Audio!G5:G122,"Must") -> 68 | D10: =COUNTIF(06_Audio!G5:G122,"Should") -> 47 | E10: =COUNTIF(06_Audio!G5:G122,"Could") -> 3 | F10: -
A11: 07_UI-Screens | B11: =COUNTA('07_UI-Screens'!A4:A48) -> 45 | C11: =COUNTIF('07_UI-Screens'!F4:F48,"Must") -> 22 | D11: =COUNTIF('07_UI-Screens'!F4:F48,"Should") -> 18 | E11: =COUNTIF('07_UI-Screens'!F4:F48,"Could") -> 5 | F11: =SUM('07_UI-Screens'!G4:G48) -> 316
A12: 08_Maps | B12: =COUNTA(08_Maps!A5:A16) -> 12 | C12: =COUNTIF(08_Maps!G5:G16,"Must") -> 6 | D12: =COUNTIF(08_Maps!G5:G16,"Should") -> 5 | E12: =COUNTIF(08_Maps!G5:G16,"Could") -> 1 | F12: =SUM(08_Maps!H5:H16) -> 279
A13: 09_Tech-Backlog | B13: =COUNTA('09_Tech-Backlog'!A4:A54) -> 51 | C13: =COUNTIF('09_Tech-Backlog'!F4:F54,"Must") -> 40 | D13: =COUNTIF('09_Tech-Backlog'!F4:F54,"Should") -> 10 | E13: =COUNTIF('09_Tech-Backlog'!F4:F54,"Could") -> 1 | F13: =SUM('09_Tech-Backlog'!G4:G54) -> 333
A14: GESAMT | B14: =SUM(B5:B13) -> 687 | C14: =SUM(C5:C13) -> 365 | D14: =SUM(D5:D13) -> 264 | E14: =SUM(E5:E13) -> 58 | F14: =SUM(F5:F13) -> 3003
A17: Hinweis zur Aufwandsschaetzung
A18: - Die Summe deckt nur die Posten ab, fuer die eine Schaetzung hinterlegt ist (Features, 3D, Animation, UI, Maps, Tech).
A19: - Nicht enthalten: Texturarbeit, VFX-Umsetzung, Audioproduktion, Projektleitung, QA-Durchfuehrung, Live-Betrieb.
A20: - Faustregel: Aufschlag von 40 bis 60 Prozent fuer Iteration, Bugfixing, Abstimmung und Unvorhergesehenes.
A21: - Aufwandsangaben sind Personentage einer erfahrenen Fachkraft der jeweiligen Disziplin, nicht Kalendertage.
